google/adk/__init__.py
google/adk/runners.py
google/adk/telemetry.py
google/adk/version.py
google/adk/agents/__init__.py
google/adk/agents/active_streaming_tool.py
google/adk/agents/base_agent.py
google/adk/agents/callback_context.py
google/adk/agents/invocation_context.py
google/adk/agents/langgraph_agent.py
google/adk/agents/live_request_queue.py
google/adk/agents/llm_agent.py
google/adk/agents/loop_agent.py
google/adk/agents/parallel_agent.py
google/adk/agents/readonly_context.py
google/adk/agents/remote_agent.py
google/adk/agents/run_config.py
google/adk/agents/sequential_agent.py
google/adk/agents/transcription_entry.py
google/adk/artifacts/__init__.py
google/adk/artifacts/base_artifact_service.py
google/adk/artifacts/gcs_artifact_service.py
google/adk/artifacts/in_memory_artifact_service.py
google/adk/auth/__init__.py
google/adk/auth/auth_credential.py
google/adk/auth/auth_handler.py
google/adk/auth/auth_preprocessor.py
google/adk/auth/auth_schemes.py
google/adk/auth/auth_tool.py
google/adk/cli/__init__.py
google/adk/cli/__main__.py
google/adk/cli/agent_graph.py
google/adk/cli/cli.py
google/adk/cli/cli_create.py
google/adk/cli/cli_deploy.py
google/adk/cli/cli_eval.py
google/adk/cli/cli_tools_click.py
google/adk/cli/fast_api.py
google/adk/cli/browser/adk_favicon.svg
google/adk/cli/browser/index.html
google/adk/cli/browser/main-G2POJE2V.js
google/adk/cli/browser/polyfills-FFHMD2TL.js
google/adk/cli/browser/styles-4VDSPQ37.css
google/adk/cli/browser/assets/audio-processor.js
google/adk/cli/browser/assets/config/runtime-config.json
google/adk/cli/utils/__init__.py
google/adk/cli/utils/envs.py
google/adk/cli/utils/evals.py
google/adk/cli/utils/logs.py
google/adk/code_executors/__init__.py
google/adk/code_executors/base_code_executor.py
google/adk/code_executors/code_execution_utils.py
google/adk/code_executors/code_executor_context.py
google/adk/code_executors/container_code_executor.py
google/adk/code_executors/unsafe_local_code_executor.py
google_adk_ta-0.4.0.dev4.dist-info/entry_points.txt
google_adk_ta-0.4.0.dev4.dist-info/LICENSE
google_adk_ta-0.4.0.dev4.dist-info/WHEEL
google_adk_ta-0.4.0.dev4.dist-info/METADATA
google_adk_ta-0.4.0.dev4.dist-info/RECORD
