Metadata-Version: 2.1
Name: google-adk-ta
Version: 0.4.0.dev4
Summary: Tiger Analytics Agent Development Kit
Author-email: Google LLC <googleapis-packages@google.com>
Requires-Python: >=3.9
Classifier: Typing :: Typed
Classifier: Intended Audience :: Developers
Classifier: Intended Audience :: Science/Research
Classifier: Programming Language :: Python
Classifier: Programming Language :: Python :: 3
Classifier: Programming Language :: Python :: 3.9
Classifier: Programming Language :: Python :: 3.13
Classifier: Programming Language :: Python :: 3.12
Classifier: Programming Language :: Python :: 3.11
Classifier: Programming Language :: Python :: 3.10
Classifier: Operating System :: OS Independent
Classifier: Topic :: Software Development :: Libraries :: Python Modules
Classifier: License :: OSI Approved :: Apache Software License
Requires-Dist: authlib>=1.5.1
Requires-Dist: click>=8.1.8
Requires-Dist: fastapi>=0.115.0
Requires-Dist: google-api-python-client>=2.157.0
Requires-Dist: google-cloud-aiplatform>=1.87.0
Requires-Dist: google-cloud-secret-manager>=2.22.0
Requires-Dist: google-cloud-speech>=2.30.0
Requires-Dist: google-cloud-storage>=2.18.0, <3.0.0
Requires-Dist: google-genai>=1.11.0
Requires-Dist: graphviz>=0.20.2
Requires-Dist: mcp>=1.5.0;python_version>='3.10'
Requires-Dist: opentelemetry-api>=1.31.0
Requires-Dist: opentelemetry-exporter-gcp-trace>=1.9.0
Requires-Dist: opentelemetry-sdk>=1.31.0
Requires-Dist: pydantic>=2.0, <3.0.0
Requires-Dist: python-dotenv>=1.0.0
Requires-Dist: PyYAML>=6.0.2
Requires-Dist: sqlalchemy>=2.0
Requires-Dist: tzlocal>=5.3
Requires-Dist: uvicorn>=0.34.0
Requires-Dist: flit>=3.10.0 ; extra == "dev"
Requires-Dist: isort>=6.0.0 ; extra == "dev"
Requires-Dist: pyink>=24.10.0 ; extra == "dev"
Requires-Dist: pylint>=2.6.0 ; extra == "dev"
Requires-Dist: autodoc_pydantic ; extra == "docs"
Requires-Dist: furo ; extra == "docs"
Requires-Dist: myst-parser ; extra == "docs"
Requires-Dist: sphinx ; extra == "docs"
Requires-Dist: sphinx-autodoc-typehints ; extra == "docs"
Requires-Dist: sphinx-rtd-theme ; extra == "docs"
Requires-Dist: google-cloud-aiplatform[evaluation]>=1.87.0 ; extra == "eval"
Requires-Dist: pandas>=2.2.3 ; extra == "eval"
Requires-Dist: tabulate>=0.9.0 ; extra == "eval"
Requires-Dist: anthropic>=0.43.0 ; extra == "extensions"
Requires-Dist: beautifulsoup4>=3.2.2 ; extra == "extensions"
Requires-Dist: crewai[tools] ; extra == "extensions" and (python_version>='3.10')
Requires-Dist: docker>=7.0.0 ; extra == "extensions"
Requires-Dist: langgraph>=0.2.60 ; extra == "extensions"
Requires-Dist: litellm>=1.63.11 ; extra == "extensions"
Requires-Dist: llama-index-readers-file>=0.4.0 ; extra == "extensions"
Requires-Dist: lxml>=5.3.0 ; extra == "extensions"
Requires-Dist: anthropic>=0.43.0 ; extra == "test"
Requires-Dist: langchain-community>=0.3.17 ; extra == "test"
Requires-Dist: langgraph>=0.2.60 ; extra == "test"
Requires-Dist: litellm>=1.63.11 ; extra == "test"
Requires-Dist: llama-index-readers-file>=0.4.0 ; extra == "test"
Requires-Dist: pytest-asyncio>=0.25.0 ; extra == "test"
Requires-Dist: pytest-mock>=3.14.0 ; extra == "test"
Requires-Dist: pytest-xdist>=3.6.1 ; extra == "test"
Requires-Dist: pytest>=8.3.4 ; extra == "test"
Project-URL: changelog, https://github.com/google/adk-python/blob/main/CHANGELOG.md
Project-URL: documentation, https://google.github.io/adk-docs/
Project-URL: homepage, https://google.github.io/adk-docs/
Project-URL: repository, https://github.com/google/adk-python
Provides-Extra: dev
Provides-Extra: docs
Provides-Extra: eval
Provides-Extra: extensions
Provides-Extra: test
